LICENSE
MANIFEST.in
README.md
setup.cfg
setup.py
3ETool.egg-info/PKG-INFO
3ETool.egg-info/SOURCES.txt
3ETool.egg-info/dependency_links.txt
3ETool.egg-info/requires.txt
3ETool.egg-info/top_level.txt
EEETools/__init__.py
EEETools/costants.py
EEETools/qrc_resources.py
EEETools/version.py
EEETools/BlockSubClasses/__init__.py
EEETools/BlockSubClasses/alternator.py
EEETools/BlockSubClasses/boiler.py
EEETools/BlockSubClasses/combustion_chamber.py
EEETools/BlockSubClasses/compressor.py
EEETools/BlockSubClasses/condenser.py
EEETools/BlockSubClasses/cooler.py
EEETools/BlockSubClasses/evaporator.py
EEETools/BlockSubClasses/expander.py
EEETools/BlockSubClasses/generic.py
EEETools/BlockSubClasses/heat_exchanger.py
EEETools/BlockSubClasses/mixer.py
EEETools/BlockSubClasses/pump.py
EEETools/BlockSubClasses/separator.py
EEETools/BlockSubClasses/valve.py
EEETools/BlockSubClasses/not_ready_subclasses/__init__.py
EEETools/BlockSubClasses/not_ready_subclasses/ejector_simplified.py
EEETools/MainModules/__init__.py
EEETools/MainModules/main_module.py
EEETools/MainModules/pf_diagram_generation_module.py
EEETools/MainModules/support_blocks.py
EEETools/Tools/__init__.py
EEETools/Tools/modules_handler.py
EEETools/Tools/API/__init__.py
EEETools/Tools/API/terminal_api.py
EEETools/Tools/API/DatAPI/__init__.py
EEETools/Tools/API/DatAPI/modules_importer.py
EEETools/Tools/API/ExcelAPI/__init__.py
EEETools/Tools/API/ExcelAPI/modules_importer.py
EEETools/Tools/API/JSONAPI/__init__.py
EEETools/Tools/API/JSONAPI/modules_importer.py
EEETools/Tools/API/JSONAPI/build/asset-manifest.json
EEETools/Tools/API/JSONAPI/build/favicon.ico
EEETools/Tools/API/JSONAPI/build/index.html
EEETools/Tools/API/JSONAPI/build/logo192.png
EEETools/Tools/API/JSONAPI/build/logo512.png
EEETools/Tools/API/JSONAPI/build/manifest.json
EEETools/Tools/API/JSONAPI/build/robots.txt
EEETools/Tools/API/JSONAPI/build/static/css/main.5c8a38e1.css
EEETools/Tools/API/JSONAPI/build/static/css/main.5c8a38e1.css.map
EEETools/Tools/API/JSONAPI/build/static/js/238.c5b75cd3.chunk.js
EEETools/Tools/API/JSONAPI/build/static/js/238.c5b75cd3.chunk.js.LICENSE.txt
