Metadata-Version: 2.1
Name: 3ETool
Version: 0.9.4
Summary: Tools for performing exergo-economic and exergo-environmental analysis
Home-page: https://tinyurl.com/SERG-3ETool
Download-URL: https://github.com/SERGGroup/3ETool/archive/refs/tags/0.9.4.tar.gz
Author: Pietro Ungar
Author-email: pietro.ungar@unifi.it
License: GNU GPLv3
Project-URL: Documentation, https://drive.google.com/file/d/1Dzdz4_EAKyY9c8nOm2SKTIqSXfV74w2-/view?usp=sharing
Project-URL: Source, https://github.com/SERGGroup/3ETool
Project-URL: Tracker, https://github.com/SERGGroup/3ETool/issues
Platform: UNKNOWN
Classifier: Development Status :: 4 - Beta
Classifier: Intended Audience :: Science/Research
Classifier: Topic :: Scientific/Engineering
Classifier: License :: OSI Approved :: GNU General Public License v3 (GPLv3)
License-File: LICENSE
